rkhs/__init__.py
rkhs/_base.py
rkhs/_util.py
rkhs/kernels.py
rkhs/py.typed
rkhs/random.py
rkhs/testing/__init__.py
rkhs/testing/_base.py
rkhs/testing/_conditional.py
rkhs/testing/_marginal.py
rkhs-0.0.1.dist-info/licenses/LICENSE
rkhs-0.0.1.dist-info/METADATA
rkhs-0.0.1.dist-info/WHEEL
rkhs-0.0.1.dist-info/top_level.txt
rkhs-0.0.1.dist-info/RECORD
