Metadata-Version: 2.4
Name: rkhs
Version: 0.0.1
Summary: A unified framework for marginal and conditional two-sample testing with kernels in JAX.
Home-page: https://github.com/lukashaverbeck/rkhs
Author: Lukas Haverbeck
License: MIT License
Project-URL: Homepage, https://github.com/lukashaverbeck/rkhs
Project-URL: Issues, https://github.com/lukashaverbeck/rkhs/issues
Keywords: kernels,jax,two-sample-test
Classifier: Programming Language :: Python :: 3
Classifier: Programming Language :: Python :: 3.12
Classifier: Programming Language :: Python :: 3.13
Classifier: License :: OSI Approved :: MIT License
Classifier: Operating System :: OS Independent
Classifier: Typing :: Typed
Requires-Python: >=3.13
License-File: LICENSE
Requires-Dist: jax>=0.7.1
Provides-Extra: dev
Requires-Dist: build>=1.2; extra == "dev"
Requires-Dist: twine>=5; extra == "dev"
Dynamic: home-page
Dynamic: license-file
Dynamic: requires-python
